{
  "data": {
    "userCarts": {
      "id": "1b6e0715",
      "carts": [
        {
          "__typename": "CartsCart",
          "id": "3693684252",
          "cartType": "grocery",
          "itemCount": 2,
          "retailerId": "200",
          "cartItemCollection": {
            "cartItems": [
              {
                "id": "34540770075",
                "quantity": 2.0,
                "quantityType": "each",
                "basketProduct": {
                  "id": "items_3113-22373938",
                  "productId": "22373938"
                }
              }
            ]
          }
        }
      ],
      "__typename": "CartsCartsCollection"
    }
  }
}
